[{"title":"Phonics 1","file":"/streaming-media/2023/01/01PH056F/01PH056F.m3u8","description":"Phonics 1 - Lesson: 56 - Teacher: Miss Howe","image":"/images/banner.jpg","type":"application/vnd.apple.mpegurl"},{"title":"Arithmetic 1: Arithmetic","file":"/streaming-media/2023/01/01AT056F/01AT056F.m3u8","description":"Arithmetic 1: Arithmetic - Lesson: 56 - Teacher: Miss Howe","image":"/images/banner.jpg","type":"application/vnd.apple.mpegurl"},{"title":"Arithmetic 1: Combination Practice","file":"/streaming-media/2023/01/01AB056F/01AB056F.m3u8","description":"Arithmetic 1: Combination Practice - Lesson: 56 - Teacher: Miss Howe","image":"/images/banner.jpg","type":"application/vnd.apple.mpegurl"},{"title":"Activities 1","file":"/streaming-media/2023/01/01AC056F/01AC056F.m3u8","description":"Activities 1 - Lesson: 56 - Teacher: Miss Howe","image":"/images/banner.jpg","type":"application/vnd.apple.mpegurl"},{"title":"Reading 1: AM Elephants","file":"/streaming-media/2023/01/01EA056F/01EA056F.m3u8","description":"Reading 1: AM Elephants - Lesson: 56 - Teacher: Miss Howe","image":"/images/banner.jpg","type":"application/vnd.apple.mpegurl"},{"title":"Reading 1: PM Elephants","file":"/streaming-media/2023/01/01EP056F/01EP056F.m3u8","description":"Reading 1: PM Elephants - Lesson: 56 - Teacher: Miss Howe","image":"/images/banner.jpg","type":"application/vnd.apple.mpegurl"},{"title":"Reading 1: AM Giraffes","file":"/streaming-media/2023/01/01GA056F/01GA056F.m3u8","description":"Reading 1: AM Giraffes - Lesson: 56 - Teacher: Miss Howe","image":"/images/banner.jpg","type":"application/vnd.apple.mpegurl"},{"title":"Reading 1: PM Giraffes","file":"/streaming-media/2023/01/01GP056F/01GP056F.m3u8","description":"Reading 1: PM Giraffes - Lesson: 56 - Teacher: Miss Howe","image":"/images/banner.jpg","type":"application/vnd.apple.mpegurl"},{"title":"Reading 1: AM Monkeys","file":"/streaming-media/2023/01/01MA056F/01MA056F.m3u8","description":"Reading 1: AM Monkeys - Lesson: 56 - Teacher: Miss Howe","image":"/images/banner.jpg","type":"application/vnd.apple.mpegurl"},{"title":"Reading 1: PM Monkeys","file":"/streaming-media/2023/01/01MP056F/01MP056F.m3u8","description":"Reading 1: PM Monkeys - Lesson: 56 - Teacher: Miss Howe","image":"/images/banner.jpg","type":"application/vnd.apple.mpegurl"},{"title":"Seatwork 1: Seatwork Explanation (Cursive)","file":"/streaming-media/2023/01/01SE056F/01SE056F.m3u8","description":"Seatwork 1: Seatwork Explanation (Cursive) - Lesson: 56 - Teacher: Miss Howe","image":"/images/banner.jpg","type":"application/vnd.apple.mpegurl"},{"title":"Seatwork 1: Seatwork Explanation (Manuscript)","file":"/streaming-media/2023/01/01SM056F/01SM056F.m3u8","description":"Seatwork 1: Seatwork Explanation (Manuscript) - Lesson: 56 - Teacher: Miss Howe","image":"/images/banner.jpg","type":"application/vnd.apple.mpegurl"},{"title":"Spelling 1","file":"/streaming-media/2023/01/01SP056F/01SP056F.m3u8","description":"Spelling 1 - Lesson: 56 - Teacher: Miss Howe","image":"/images/banner.jpg","type":"application/vnd.apple.mpegurl"},{"title":"Writing 1: Cursive Writing","file":"/streaming-media/2023/01/01CW056F/01CW056F.m3u8","description":"Writing 1: Cursive Writing - Lesson: 56 - Teacher: Miss Howe","image":"/images/banner.jpg","type":"application/vnd.apple.mpegurl"},{"title":"Writing 1: Manuscript Writing","file":"/streaming-media/2023/01/01MW056F/01MW056F.m3u8","description":"Writing 1: Manuscript Writing - Lesson: 56 - Teacher: Miss Howe","image":"/images/banner.jpg","type":"application/vnd.apple.mpegurl"},{"title":"Bible 1","file":"/streaming-media/2023/01/01BI056F/01BI056F.m3u8","description":"Bible 1 - Lesson: 56 - Teacher: Miss Howe","image":"/images/banner.jpg","type":"application/vnd.apple.mpegurl"}]