[{"title":"English 9","file":"/streaming-media/2023/09/09EN120E/09EN120E.m3u8","description":"English 9 - Lesson: 120 - Teacher: Mr. Bucy","image":"/images/banner.jpg","type":"application/vnd.apple.mpegurl"},{"title":"Physical Science","file":"/streaming-media/2023/09/09PS120D/09PS120D.m3u8","description":"Physical Science - Lesson: 120 - Teacher: Dr. Ridgley","image":"/images/banner.jpg","type":"application/vnd.apple.mpegurl"},{"title":"Hebrew History","file":"/streaming-media/2023/09/09HH120E/09HH120E.m3u8","description":"Hebrew History - Lesson: 120 - Teacher: Mr. Smith","image":"/images/banner.jpg","type":"application/vnd.apple.mpegurl"},{"title":"Algebra 1","file":"/streaming-media/2023/09/09A1120G/09A1120G.m3u8","description":"Algebra 1 - Lesson: 120 - Teacher: Mrs. Turner","image":"/images/banner.jpg","type":"application/vnd.apple.mpegurl"}]