[{"title":"Language 6","file":"/streaming-media/2023/06/06LA100F/06LA100F.m3u8","description":"Language 6 - Lesson: 100 - Teacher: Mrs. Tupua","image":"/images/banner.jpg","type":"application/vnd.apple.mpegurl"},{"title":"Arithmetic 6","file":"/streaming-media/2023/06/06AT100F/06AT100F.m3u8","description":"Arithmetic 6 - Lesson: 100 - Teacher: Mr. Howe","image":"/images/banner.jpg","type":"application/vnd.apple.mpegurl"},{"title":"Science 6","file":"/streaming-media/2023/06/06SC100F/06SC100F.m3u8","description":"Science 6 - Lesson: 100 - Teacher: Miss Lewis","image":"/images/banner.jpg","type":"application/vnd.apple.mpegurl"},{"title":"Penmanship 6","file":"/streaming-media/2023/06/06PN100F/06PN100F.m3u8","description":"Penmanship 6 - Lesson: 100 - Teacher: Mrs. Tupua","image":"/images/banner.jpg","type":"application/vnd.apple.mpegurl"},{"title":"Reading 6","file":"/streaming-media/2023/06/06RE100F/06RE100F.m3u8","description":"Reading 6 - Lesson: 100 - Teacher: Miss Moses","image":"/images/banner.jpg","type":"application/vnd.apple.mpegurl"},{"title":"Spelling 6","file":"/streaming-media/2023/06/06SP100F/06SP100F.m3u8","description":"Spelling 6 - Lesson: 100 - Teacher: Mrs. Tupua","image":"/images/banner.jpg","type":"application/vnd.apple.mpegurl"},{"title":"History 6","file":"/streaming-media/2023/06/06HI100F/06HI100F.m3u8","description":"History 6 - Lesson: 100 - Teacher: Miss Lewis","image":"/images/banner.jpg","type":"application/vnd.apple.mpegurl"},{"title":"Bible 6","file":"/streaming-media/2023/06/06BI100F/06BI100F.m3u8","description":"Bible 6 - Lesson: 100 - Teacher: Mrs. Tupua","image":"/images/banner.jpg","type":"application/vnd.apple.mpegurl"}]