[{"title":"Phonics and Language 2","file":"/streaming-media/2023/02/02PH114F/02PH114F.m3u8","description":"Phonics and Language 2 - Lesson: 114 - Teacher: Mrs. Chappell","image":"/images/banner.jpg","type":"application/vnd.apple.mpegurl"},{"title":"Arithmetic 2: Arithmetic","file":"/streaming-media/2023/02/02AT114F/02AT114F.m3u8","description":"Arithmetic 2: Arithmetic - Lesson: 114 - Teacher: Mrs. Chappell","image":"/images/banner.jpg","type":"application/vnd.apple.mpegurl"},{"title":"Arithmetic 2: Arithmetic Combinations","file":"/streaming-media/2023/02/02AB114F/02AB114F.m3u8","description":"Arithmetic 2: Arithmetic Combinations - Lesson: 114 - Teacher: Mrs. Chappell","image":"/images/banner.jpg","type":"application/vnd.apple.mpegurl"},{"title":"Activities 2","file":"/streaming-media/2023/02/02AC114F/02AC114F.m3u8","description":"Activities 2 - Lesson: 114 - Teacher: Mrs. Chappell","image":"/images/banner.jpg","type":"application/vnd.apple.mpegurl"},{"title":"Reading 2: AM Class Reading","file":"/streaming-media/2023/02/02RA114F/02RA114F.m3u8","description":"Reading 2: AM Class Reading - Lesson: 114 - Teacher: Mrs. Chappell","image":"/images/banner.jpg","type":"application/vnd.apple.mpegurl"},{"title":"Reading 2: PM Birds","file":"/streaming-media/2023/02/02PD114F/02PD114F.m3u8","description":"Reading 2: PM Birds - Lesson: 114 - Teacher: Mrs. Chappell","image":"/images/banner.jpg","type":"application/vnd.apple.mpegurl"},{"title":"Reading 2: PM Beavers","file":"/streaming-media/2023/02/02PV114F/02PV114F.m3u8","description":"Reading 2: PM Beavers - Lesson: 114 - Teacher: Mrs. Chappell","image":"/images/banner.jpg","type":"application/vnd.apple.mpegurl"},{"title":"Seatwork 2","file":"/streaming-media/2023/02/02SE114F/02SE114F.m3u8","description":"Seatwork 2 - Lesson: 114 - Teacher: Mrs. Chappell","image":"/images/banner.jpg","type":"application/vnd.apple.mpegurl"},{"title":"Spelling 2","file":"/streaming-media/2023/02/02SP114F/02SP114F.m3u8","description":"Spelling 2 - Lesson: 114 - Teacher: Mrs. Chappell","image":"/images/banner.jpg","type":"application/vnd.apple.mpegurl"},{"title":"Writing 2","file":"/streaming-media/2023/02/02WR114F/02WR114F.m3u8","description":"Writing 2 - Lesson: 114 - Teacher: Mrs. Chappell","image":"/images/banner.jpg","type":"application/vnd.apple.mpegurl"},{"title":"Bible 2","file":"/streaming-media/2023/02/02BI114F/02BI114F.m3u8","description":"Bible 2 - Lesson: 114 - Teacher: Mrs. Chappell","image":"/images/banner.jpg","type":"application/vnd.apple.mpegurl"}]