[{"title":"Phonics and Language 2","file":"/streaming-media/2023/02/02PH167F/02PH167F.m3u8","description":"Phonics and Language 2 - Lesson: 167 - Teacher: Mrs. Chappell","image":"/images/banner.jpg","type":"application/vnd.apple.mpegurl"},{"title":"Arithmetic 2: Arithmetic","file":"/streaming-media/2023/02/02AT167F/02AT167F.m3u8","description":"Arithmetic 2: Arithmetic - Lesson: 167 - Teacher: Mrs. Chappell","image":"/images/banner.jpg","type":"application/vnd.apple.mpegurl"},{"title":"Arithmetic 2: Arithmetic Combinations","file":"/streaming-media/2023/02/02AB167F/02AB167F.m3u8","description":"Arithmetic 2: Arithmetic Combinations - Lesson: 167 - Teacher: Mrs. Chappell","image":"/images/banner.jpg","type":"application/vnd.apple.mpegurl"},{"title":"Activities 2","file":"/streaming-media/2023/02/02AC167F/02AC167F.m3u8","description":"Activities 2 - Lesson: 167 - Teacher: Mrs. Chappell","image":"/images/banner.jpg","type":"application/vnd.apple.mpegurl"},{"title":"Reading 2: AM Class Reading","file":"/streaming-media/2023/02/02RA167F/02RA167F.m3u8","description":"Reading 2: AM Class Reading - Lesson: 167 - Teacher: Mrs. Chappell","image":"/images/banner.jpg","type":"application/vnd.apple.mpegurl"},{"title":"Reading 2: PM Birds","file":"/streaming-media/2023/02/02PD167F/02PD167F.m3u8","description":"Reading 2: PM Birds - Lesson: 167 - Teacher: Mrs. Chappell","image":"/images/banner.jpg","type":"application/vnd.apple.mpegurl"},{"title":"Seatwork 2","file":"/streaming-media/2023/02/02SE167F/02SE167F.m3u8","description":"Seatwork 2 - Lesson: 167 - Teacher: Mrs. Chappell","image":"/images/banner.jpg","type":"application/vnd.apple.mpegurl"},{"title":"Spelling 2","file":"/streaming-media/2023/02/02SP167F/02SP167F.m3u8","description":"Spelling 2 - Lesson: 167 - Teacher: Mrs. Chappell","image":"/images/banner.jpg","type":"application/vnd.apple.mpegurl"},{"title":"Writing 2","file":"/streaming-media/2023/02/02WR167F/02WR167F.m3u8","description":"Writing 2 - Lesson: 167 - Teacher: Mrs. Chappell","image":"/images/banner.jpg","type":"application/vnd.apple.mpegurl"},{"title":"Bible 2","file":"/streaming-media/2023/02/02BI167F/02BI167F.m3u8","description":"Bible 2 - Lesson: 167 - Teacher: Mrs. Chappell","image":"/images/banner.jpg","type":"application/vnd.apple.mpegurl"}]