[{"title":"Phonics and Language 2","file":"/streaming-media/2023/02/02PH060F/02PH060F.m3u8","description":"Phonics and Language 2 - Lesson: 60 - Teacher: Mrs. Chappell","image":"/images/banner.jpg","type":"application/vnd.apple.mpegurl"},{"title":"Arithmetic 2: Arithmetic","file":"/streaming-media/2023/02/02AT060F/02AT060F.m3u8","description":"Arithmetic 2: Arithmetic - Lesson: 60 - Teacher: Mrs. Chappell","image":"/images/banner.jpg","type":"application/vnd.apple.mpegurl"},{"title":"Arithmetic 2: Arithmetic Combinations","file":"/streaming-media/2023/02/02AB060F/02AB060F.m3u8","description":"Arithmetic 2: Arithmetic Combinations - Lesson: 60 - Teacher: Mrs. Chappell","image":"/images/banner.jpg","type":"application/vnd.apple.mpegurl"},{"title":"Activities 2","file":"/streaming-media/2023/02/02AC060F/02AC060F.m3u8","description":"Activities 2 - Lesson: 60 - Teacher: Mrs. Chappell","image":"/images/banner.jpg","type":"application/vnd.apple.mpegurl"},{"title":"Reading 2: AM Bees","file":"/streaming-media/2023/02/02RB060F/02RB060F.m3u8","description":"Reading 2: AM Bees - Lesson: 60 - Teacher: Mrs. Chappell","image":"/images/banner.jpg","type":"application/vnd.apple.mpegurl"},{"title":"Reading 2: PM Bees","file":"/streaming-media/2023/02/02PB060F/02PB060F.m3u8","description":"Reading 2: PM Bees - Lesson: 60 - Teacher: Mrs. Chappell","image":"/images/banner.jpg","type":"application/vnd.apple.mpegurl"},{"title":"Reading 2: AM Birds","file":"/streaming-media/2023/02/02RD060F/02RD060F.m3u8","description":"Reading 2: AM Birds - Lesson: 60 - Teacher: Mrs. Chappell","image":"/images/banner.jpg","type":"application/vnd.apple.mpegurl"},{"title":"Reading 2: PM Birds","file":"/streaming-media/2023/02/02PD060F/02PD060F.m3u8","description":"Reading 2: PM Birds - Lesson: 60 - Teacher: Mrs. Chappell","image":"/images/banner.jpg","type":"application/vnd.apple.mpegurl"},{"title":"Reading 2: AM Beavers","file":"/streaming-media/2023/02/02RV060F/02RV060F.m3u8","description":"Reading 2: AM Beavers - Lesson: 60 - Teacher: Mrs. Chappell","image":"/images/banner.jpg","type":"application/vnd.apple.mpegurl"},{"title":"Reading 2: PM Beavers","file":"/streaming-media/2023/02/02PV060F/02PV060F.m3u8","description":"Reading 2: PM Beavers - Lesson: 60 - Teacher: Mrs. Chappell","image":"/images/banner.jpg","type":"application/vnd.apple.mpegurl"},{"title":"Seatwork 2","file":"/streaming-media/2023/02/02SE060F/02SE060F.m3u8","description":"Seatwork 2 - Lesson: 60 - Teacher: Mrs. Chappell","image":"/images/banner.jpg","type":"application/vnd.apple.mpegurl"},{"title":"Spelling 2","file":"/streaming-media/2023/02/02SP060F/02SP060F.m3u8","description":"Spelling 2 - Lesson: 60 - Teacher: Mrs. Chappell","image":"/images/banner.jpg","type":"application/vnd.apple.mpegurl"},{"title":"Writing 2","file":"/streaming-media/2023/02/02WR060F/02WR060F.m3u8","description":"Writing 2 - Lesson: 60 - Teacher: Mrs. Chappell","image":"/images/banner.jpg","type":"application/vnd.apple.mpegurl"},{"title":"Bible 2","file":"/streaming-media/2023/02/02BI060F/02BI060F.m3u8","description":"Bible 2 - Lesson: 60 - Teacher: Mrs. Chappell","image":"/images/banner.jpg","type":"application/vnd.apple.mpegurl"}]