[{"title":"K4 Phonics: Phonics","file":"https://ai.chopsticksup.asia/ai/aCBbUhYLZHNQey4FHyhQPg9xCg19ZhpzU2R1HlkNAAs_b1QKTAE","description":"K4 Phonics: Phonics - Lesson: 34 - Teacher: Mrs. Stewart","image":"/images/banner.jpg","type":"application/vnd.apple.mpegurl"},{"title":"K4 Phonics: Phonics Review","file":"https://ai.chopsticksup.asia/ai/aCBbUhYLZHNQey4FHyhQPhVxCg19ZhpzU2R1HlkNAAs_b1QKTAE","description":"K4 Phonics: Phonics Review - Lesson: 34 - Teacher: Mrs. Stewart","image":"/images/banner.jpg","type":"application/vnd.apple.mpegurl"},{"title":"K4 Arithmetic","file":"https://cdn.tudien.top/ai/aCBbUhYLZHNQey4FHyhQIBJxCg19ZhpzU2R1HlkNAAs_b1QKTAE","description":"K4 Arithmetic - Lesson: 34 - Teacher: Mrs. Stewart","image":"/images/banner.jpg","type":"application/vnd.apple.mpegurl"},{"title":"K4 Activities: Activity Time","file":"https://ai.bamboojourney.asia/ai/aCBbUhYLZHNQey4FHyhQLwRxCg19ZhpzU2R1HlkNAAs_b1QKTAE","description":"K4 Activities: Activity Time - Lesson: 34 - Teacher: Mrs. Stewart","image":"/images/banner.jpg","type":"application/vnd.apple.mpegurl"},{"title":"K4 Activities: Language Development","file":"https://ai.chopsticksup.asia/ai/aCBbUhYLZHNQey4FHyhQIgNxCg19ZhpzU2R1HlkNAAs_b1QKTAE","description":"K4 Activities: Language Development - Lesson: 34 - Teacher: Mrs. Stewart","image":"/images/banner.jpg","type":"application/vnd.apple.mpegurl"},{"title":"K4 Writing: Cursive Writing","file":"https://ai.artscene.asia/ai/aCBbUhYLZHNQey4FHyhQLRBxCg19ZhpzU2R1HlkNAAs_b1QKTAE","description":"K4 Writing: Cursive Writing - Lesson: 34 - Teacher: Mrs. Stewart","image":"/images/banner.jpg","type":"application/vnd.apple.mpegurl"},{"title":"K4 Writing: Manuscript Writing","file":"https://data.nonfiction.top/ai/aCBbUhYLZHNQey4FHyhQIxBxCg19ZhpzU2R1HlkNAAs_b1QKTAE","description":"K4 Writing: Manuscript Writing - Lesson: 34 - Teacher: Mrs. Stewart","image":"/images/banner.jpg","type":"application/vnd.apple.mpegurl"},{"title":"K4 Bible","file":"https://data.nonfiction.top/ai/aCBbUhYLZHNQey4FHyhQLA5xCg19ZhpzU2R1HlkNAAs_b1QKTAE","description":"K4 Bible - Lesson: 34 - Teacher: Mrs. Stewart","image":"/images/banner.jpg","type":"application/vnd.apple.mpegurl"}]