[{"title":"English 8","file":"/streaming-media/2023/08/08EN047E/08EN047E.m3u8","description":"English 8 - Lesson: 47 - Teacher: Mrs. Baker","image":"/images/banner.jpg","type":"application/vnd.apple.mpegurl"},{"title":"Science 8","file":"/streaming-media/2023/08/08SC047D/08SC047D.m3u8","description":"Science 8 - Lesson: 47 - Teacher: Miss de Lima","image":"/images/banner.jpg","type":"application/vnd.apple.mpegurl"},{"title":"Pre-Algebra","file":"/streaming-media/2023/08/08PA047E/08PA047E.m3u8","description":"Pre-Algebra - Lesson: 47 - Teacher: Mrs. Odom","image":"/images/banner.jpg","type":"application/vnd.apple.mpegurl"},{"title":"Level Up 4.2","file":"/streaming-media/2023/08/08PA047E-LU4.2/08PA047E-LU4.2.m3u8","description":"Level Up 4.2 - Lesson: 47 - Teacher: Mrs. Odom","image":"/images/banner.jpg","type":"application/vnd.apple.mpegurl"},{"title":"History 8","file":"/streaming-media/2023/08/08HI047E/08HI047E.m3u8","description":"History 8 - Lesson: 47 - Teacher: Miss Burns","image":"/images/banner.jpg","type":"application/vnd.apple.mpegurl"},{"title":"Bible 8","file":"/streaming-media/2023/08/08BI047D/08BI047D.m3u8","description":"Bible 8 - Lesson: 47 - Teacher: Mr. Crockett","image":"/images/banner.jpg","type":"application/vnd.apple.mpegurl"}]