[{"title":"English 12","file":"/streaming-media/2023/12/12EN111E/12EN111E.m3u8","description":"English 12 - Lesson: 111 - Teacher: Mr. Bucy","image":"/images/banner.jpg","type":"application/vnd.apple.mpegurl"},{"title":"Precalculus","file":"/streaming-media/2023/12/12PC111C/12PC111C.m3u8","description":"Precalculus - Lesson: 111 - Teacher: Mr. Collins","image":"/images/banner.jpg","type":"application/vnd.apple.mpegurl"},{"title":"Physics","file":"/streaming-media/2023/12/12PH111C/12PH111C.m3u8","description":"Physics - Lesson: 111 - Teacher: Dr. Ridgley","image":"/images/banner.jpg","type":"application/vnd.apple.mpegurl"},{"title":"Spanish 2","file":"/streaming-media/2023/12/12SA111D/12SA111D.m3u8","description":"Spanish 2 - Lesson: 111 - Teacher: Miss Quinlan","image":"/images/banner.jpg","type":"application/vnd.apple.mpegurl"}]