[{"title":"K5 Phonics","file":"/streaming-media/2023/k5/K5PH170D/K5PH170D.m3u8","description":"K5 Phonics - Lesson: 170 - Teacher: Mrs. Turner","image":"/images/banner.jpg","type":"application/vnd.apple.mpegurl"},{"title":"K5 Numbers","file":"/streaming-media/2023/k5/K5NU170D/K5NU170D.m3u8","description":"K5 Numbers - Lesson: 170 - Teacher: Mrs. Turner","image":"/images/banner.jpg","type":"application/vnd.apple.mpegurl"},{"title":"K5 Activities","file":"/streaming-media/2023/k5/K5SD170D/K5SD170D.m3u8","description":"K5 Activities - Lesson: 170 - Teacher: Mrs. Turner","image":"/images/banner.jpg","type":"application/vnd.apple.mpegurl"},{"title":"K5 Bible","file":"/streaming-media/2023/k5/K5BI170D/K5BI170D.m3u8","description":"K5 Bible - Lesson: 170 - Teacher: Mrs. Turner","image":"/images/banner.jpg","type":"application/vnd.apple.mpegurl"}]